rkoMadness/__init__.py
rkoMadness-1.0.5.data/scripts/rkomadness
rkoMadness-1.0.5.dist-info/METADATA
rkoMadness-1.0.5.dist-info/RECORD
rkoMadness-1.0.5.dist-info/WHEEL
rkoMadness-1.0.5.dist-info/top_level.txt
